AUTHORS
ChangeLog
HACKING.rst
README.rst
run-sandbox
sandbox.py
setup.cfg
setup.py
tox.ini
sandboxlib/__init__.py
sandboxlib/chroot.py
sandboxlib/linux_user_chroot.py
sandboxlib/utils.py
sandboxlib.egg-info/PKG-INFO
sandboxlib.egg-info/SOURCES.txt
sandboxlib.egg-info/dependency_links.txt
sandboxlib.egg-info/not-zip-safe
sandboxlib.egg-info/pbr.json
sandboxlib.egg-info/top_level.txt
sandboxlib/load/__init__.py
sandboxlib/load/appc.py
tests/programs.py
tests/test_all.py