Metadata-Version: 1.0
Name: sandboxlib
Version: 0.3.0
Summary: Sandboxing Library for Python
Home-page: UNKNOWN
Author: UNKNOWN
Author-email: UNKNOWN
License: GPL2
Platform: UNKNOWN
